tilib/__init__.py
tilib/indicators.py
TI_Lib-0.0.1.dist-info/LICENSE
TI_Lib-0.0.1.dist-info/METADATA
TI_Lib-0.0.1.dist-info/WHEEL
TI_Lib-0.0.1.dist-info/top_level.txt
TI_Lib-0.0.1.dist-info/RECORD
