Metadata-Version: 2.1
Name: TI-Lib
Version: 0.0.1
Summary: This is a technical indicators library which is highly useful in the technical analysis of stock market data.
Home-page: https://github.com/Nitul067/TI-Lib
Author: Nitul Rupareliya
Author-email: nvr.job99@gmail.com
Classifier: Programming Language :: Python :: 3.10
Classifier: License :: OSI Approved :: MIT License
Classifier: Operating System :: OS Independent
Requires-Python: >=3.10
License-File: LICENSE
Requires-Dist: numpy
Requires-Dist: pandas
